autodistill_roboflow_universe/__init__.py
autodistill_roboflow_universe/roboflow_universe_model.py
autodistill_roboflow_universe-0.1.1.dist-info/LICENSE
autodistill_roboflow_universe-0.1.1.dist-info/METADATA
autodistill_roboflow_universe-0.1.1.dist-info/WHEEL
autodistill_roboflow_universe-0.1.1.dist-info/top_level.txt
autodistill_roboflow_universe-0.1.1.dist-info/RECORD
